{
    "backend": "flask",
    "db_name": "",
    "db_pass": "",
    "db_type": "sqlite",
    "db_user": "",
    "dbms": "1",
    "description": "generated product",
    "design": "material-kit",
    "docker": "1",
    "err_code": 0,
    "frontend": "",
    "heroku": "0",
    "pattern": "mvc",
    "pro": "0",
    "task_id": "828f6d59-0c62-4b8e-a71f-e237f7b03366",
    "task_info": "Upload Sources [0%] - 349 files",
    "task_output": "828f6d59-0c62-4b8e-a71f-e237f7b03366.zip",
    "task_result": "SUCCESS",
    "task_state": "RUNNING",
    "task_ts_end": "2023-09-02-12-30-24",
    "task_ts_start": "2023-09-02-12-30-22"
}